{
    "": [
        "\u5fc3\u6d41\u603b\u7ed3.md", 
        "cool facts in winter.md", 
        "preface.md", 
        "readme.md", 
        "chapter 1", 
        "chapter 2", 
        "chapter3", 
        "chapter 4", 
        "chapter 5", 
        "chapter 6", 
        "chapter 7", 
        "chapter 8", 
        "chapter 9", 
        "chapter 10"
    ], 
    "chapter3": [
        "images"
    ], 
    "chapter 9": [
        "2020-04-06.md", 
        "2020-04-05.md", 
        "2020-04-04.txt", 
        "2020-04-02.md", 
        "readme.md"
    ], 
    "chapter 10": [
        "2020-04-10.md", 
        "2020-04-09.md", 
        "2020-04-08.md", 
        "readme.md"
    ], 
    "chapter 8": [
        "2020-04-01.md", 
        "2020-03-31.md", 
        "\u5982\u4f55\u4eab\u53d7\u5b64\u72ec.md", 
        "readme.md"
    ], 
    "__positions": {
        "chapter 6": 10, 
        "chapter 7": 11, 
        "chapter 4": 8, 
        "chapter 5": 9, 
        "chapter 2": 6, 
        "chapter 1": 5, 
        "preface.md": 3, 
        "chapter 10/2020-04-10.md": 14001, 
        "chapter 8/2020-04-01.md": 12001, 
        "chapter 8": 12, 
        "chapter 9": 13, 
        "chapter 10": 14, 
        "chapter 9/readme.md": 13005, 
        "chapter 10/2020-04-08.md": 14003, 
        "chapter 8/readme.md": 12004, 
        "chapter 8/2020-03-31.md": 12002, 
        "cool facts in winter.md": 2, 
        "chapter3": 7, 
        "chapter 9/2020-04-02.md": 13004, 
        "chapter 9/2020-04-06.md": 13001, 
        "readme.md": 4, 
        "chapter 10/readme.md": 14004, 
        "chapter3/images": 7001, 
        "chapter 8/\u5982\u4f55\u4eab\u53d7\u5b64\u72ec.md": 12003, 
        "\u5fc3\u6d41\u603b\u7ed3.md": 1, 
        "chapter 9/2020-04-04.txt": 13003, 
        "chapter 10/2020-04-09.md": 14002, 
        "chapter 9/2020-04-05.md": 13002
    }, 
    "__raw_positions": {
        "chapter 6": 10, 
        "chapter 7": 11, 
        "chapter 4": 8, 
        "chapter 5": 9, 
        "chapter 2": 6, 
        "chapter 1": 5, 
        "preface.md": 3, 
        "chapter 10/2020-04-10.md": 1, 
        "chapter 8/2020-04-01.md": 1, 
        "chapter 8": 12, 
        "chapter 9": 13, 
        "chapter 10": 14, 
        "chapter 9/readme.md": 5, 
        "chapter 10/2020-04-08.md": 3, 
        "chapter 8/readme.md": 4, 
        "chapter 8/2020-03-31.md": 2, 
        "cool facts in winter.md": 2, 
        "chapter3": 7, 
        "chapter 9/2020-04-02.md": 4, 
        "chapter 9/2020-04-06.md": 1, 
        "readme.md": 4, 
        "chapter 10/readme.md": 4, 
        "chapter3/images": 1, 
        "chapter 8/\u5982\u4f55\u4eab\u53d7\u5b64\u72ec.md": 3, 
        "\u5fc3\u6d41\u603b\u7ed3.md": 1, 
        "chapter 9/2020-04-04.txt": 3, 
        "chapter 10/2020-04-09.md": 2, 
        "chapter 9/2020-04-05.md": 2
    }
}